colossus_ltsm/__init__.py
colossus_ltsm/colossus_main.py
colossus_ltsm/font_converter.py
colossus_ltsm/font_viewer.py
colossus_ltsm/settings.py
colossus_ltsm-0.1.0.dist-info/LICENSE
colossus_ltsm-0.1.0.dist-info/METADATA
colossus_ltsm-0.1.0.dist-info/WHEEL
colossus_ltsm-0.1.0.dist-info/entry_points.txt
colossus_ltsm-0.1.0.dist-info/top_level.txt
colossus_ltsm-0.1.0.dist-info/RECORD
