Metadata-Version: 2.1
Name: colossus-ltsm
Version: 0.1.0
Summary: Font, bitmap conversion and visualization tool for embedded systems
Author-email: Gavin Lyons <glyons66@hotmail.com>
Project-URL: Homepage, https://github.com/gavinlyonsrepo/Colossus_LTSM
Project-URL: Issues, https://github.com/gavinlyonsrepo/Colossus_LTSM/issues
Keywords: fonts,bitmap,converter,embedded,lcd,gui
Classifier: Development Status :: 3 - Alpha
Classifier: Programming Language :: Python :: 3
Classifier: Operating System :: OS Independent
Requires-Python: >=3.8
License-File: LICENSE
Requires-Dist: Pillow
